CHANGELOG.md
LICENSE
MANIFEST.in
README.md
setup.cfg
setup.py
suncalc/__init__.py
suncalc/suncalc.py
suncalc.egg-info/PKG-INFO
suncalc.egg-info/SOURCES.txt
suncalc.egg-info/dependency_links.txt
suncalc.egg-info/not-zip-safe
suncalc.egg-info/requires.txt
suncalc.egg-info/top_level.txt