Metadata-Version: 2.1
Name: suncalc
Version: 0.1.3
Summary: A fast, vectorized Python port of suncalc.js
Home-page: https://github.com/kylebarron/suncalc-py
Author: Kyle Barron
Author-email: kylebarron2@gmail.com
License: MIT license
Keywords: suncalc,sun
Classifier: Development Status :: 4 - Beta
Classifier: Intended Audience :: Developers
Classifier: License :: OSI Approved :: MIT License
Classifier: Natural Language :: English
Classifier: Programming Language :: Python :: 3
Classifier: Programming Language :: Python :: 3.6
Classifier: Programming Language :: Python :: 3.7
Classifier: Programming Language :: Python :: 3.8
Classifier: Programming Language :: Python :: 3.9
Classifier: Programming Language :: Python :: 3.10
Classifier: Programming Language :: Python :: 3.11
Requires-Python: >=3.6
Provides-Extra: pandas
Provides-Extra: tests
License-File: LICENSE
